flask_pyoidc/__init__.py
flask_pyoidc/auth_response_handler.py
flask_pyoidc/flask_pyoidc.py
flask_pyoidc/parse_fragment.html
flask_pyoidc/provider_configuration.py
flask_pyoidc/pyoidc_facade.py
flask_pyoidc/rbac_checker.py
flask_pyoidc/user_session.py
Flask_pyoidc_oda-0.6.3.dist-info/LICENSE
Flask_pyoidc_oda-0.6.3.dist-info/METADATA
Flask_pyoidc_oda-0.6.3.dist-info/WHEEL
Flask_pyoidc_oda-0.6.3.dist-info/top_level.txt
Flask_pyoidc_oda-0.6.3.dist-info/RECORD
