Metadata-Version: 2.1
Name: Flask-pyoidc-oda
Version: 0.6.3
Summary: Flask extension for OpenID Connect authentication, modified for use at ODA.
Home-page: https://github.com/KLMatlock/Flask-pyoidc-oda
Author: Kevin Matlock
Author-email: kevin.matlock@omicsautomation.com
License: Apache 2.0
Platform: UNKNOWN
Requires-Dist: oic (==1.2.1)
Requires-Dist: Flask
Requires-Dist: requests
Requires-Dist: importlib-resources
Requires-Dist: PyJWT (==2.1.0)
